entity_embed/__init__.py
entity_embed/cli.py
entity_embed/data_modules.py
entity_embed/early_stopping.py
entity_embed/entity_embed.py
entity_embed/evaluation.py
entity_embed/helpers.py
entity_embed/indexes.py
entity_embed/models.py
entity_embed/benchmarks/__init__.py
entity_embed/benchmarks/abt_buy.py
entity_embed/benchmarks/amazon_google.py
entity_embed/benchmarks/base.py
entity_embed/benchmarks/beer.py
entity_embed/benchmarks/company.py
entity_embed/benchmarks/dblp_acm_structured.py
entity_embed/benchmarks/dblp_scholar_structured.py
entity_embed/benchmarks/fodors_zagats.py
entity_embed/benchmarks/itunes_amazon_structured.py
entity_embed/benchmarks/walmart_amazon_structured.py
entity_embed/data_utils/__init__.py
entity_embed/data_utils/datasets.py
entity_embed/data_utils/field_config_parser.py
entity_embed/data_utils/numericalizer.py
entity_embed/data_utils/union_find.py
entity_embed/data_utils/utils.py
entity_embed-0.0.6.dist-info/AUTHORS.rst
entity_embed-0.0.6.dist-info/LICENSE
entity_embed-0.0.6.dist-info/METADATA
entity_embed-0.0.6.dist-info/WHEEL
entity_embed-0.0.6.dist-info/entry_points.txt
entity_embed-0.0.6.dist-info/top_level.txt
entity_embed-0.0.6.dist-info/RECORD
