Metadata-Version: 2.1
Name: entity-embed
Version: 0.0.6
Summary: Transform entities like companies, products, etc. into vectors to support scalable Record Linkage / Entity Resolution using Approximate Nearest Neighbors.
Home-page: https://github.com/vintasoftware/entity-embed
Author: Flávio Juvenal (Vinta Software)
Author-email: flavio@vinta.com.br
License: MIT license
Keywords: record linkage,entity resolution,deduplication,embedding
Platform: UNKNOWN
Classifier: Development Status :: 2 - Pre-Alpha
Classifier: Intended Audience :: Developers
Classifier: License :: OSI Approved :: MIT License
Classifier: Natural Language :: English
Classifier: Programming Language :: Python :: 3
Classifier: Programming Language :: Python :: 3.6
Classifier: Programming Language :: Python :: 3.7
Classifier: Programming Language :: Python :: 3.8
Classifier: Programming Language :: Python :: 3.9
Requires-Python: >=3.6
Requires-Dist: click (<8.0,==7.1.2)
Requires-Dist: more-itertools (<9.0,>=8.6.0)
Requires-Dist: n2 (<1.2,>=0.1.7)
Requires-Dist: numpy (>=1.19.0)
Requires-Dist: ordered-set (>=4.0.2)
Requires-Dist: pytorch-lightning (<1.3,>=1.1.6)
Requires-Dist: pytorch-metric-learning (<1.0,>=0.9.98)
Requires-Dist: regex (>=2020.11.13)
Requires-Dist: torch (<1.9,>=1.7.1)
Requires-Dist: torchtext (<0.10,>=0.8)
Requires-Dist: torchvision (>=0.8.2<0.10)
Requires-Dist: tqdm (>=4.53.0)
